atlassian_atc_manager/__init__.py
atlassian_atc_manager/main.py
atlassian_atc_manager/cli/__init__.py
atlassian_atc_manager/cli/appApi.py
atlassian_atc_manager/cli/appCli.py
atlassian_atc_manager/utils/__init__.py
atlassian_atc_manager/utils/appConfig.py
atlassian_atc_manager/utils/appExractor.py
atlassian_atc_manager/utils/appLogger.py
atlassian_atc_manager/utils/appXrayCloud.py
atlassian_atc_manager/utils/appXrayDC.py
atlassian_auto_test_case_manager-0.2.2.dist-info/licenses/LICENSE
atlassian_auto_test_case_manager-0.2.2.dist-info/METADATA
atlassian_auto_test_case_manager-0.2.2.dist-info/WHEEL
atlassian_auto_test_case_manager-0.2.2.dist-info/entry_points.txt
atlassian_auto_test_case_manager-0.2.2.dist-info/top_level.txt
atlassian_auto_test_case_manager-0.2.2.dist-info/RECORD
