Metadata-Version: 2.4
Name: atlassian-auto-test-case-manager
Version: 0.2.2
Summary: Extract test cases from your codebase and push them into Jira with a single command.
Home-page: https://github.com/TMAN-Lab/tman-atlassian-atc-manager
Author: Will
Author-email: will.shi@tman.ltd
Maintainer: Will
Maintainer-email: will.shi@tman.ltd
License: Apache
Platform: linux
License-File: LICENSE
Requires-Dist: PyYAML
Requires-Dist: tabulate
Requires-Dist: requests
Dynamic: author
Dynamic: author-email
Dynamic: description
Dynamic: description-content-type
Dynamic: home-page
Dynamic: license
Dynamic: license-file
Dynamic: maintainer
Dynamic: maintainer-email
Dynamic: platform
Dynamic: requires-dist
Dynamic: summary
